setup.py
distributions_ms_dsnd/Binomialdistribution.py
distributions_ms_dsnd/Gaussiandistribution.py
distributions_ms_dsnd/Generaldistribution.py
distributions_ms_dsnd/__init__.py
distributions_ms_dsnd.egg-info/PKG-INFO
distributions_ms_dsnd.egg-info/SOURCES.txt
distributions_ms_dsnd.egg-info/dependency_links.txt
distributions_ms_dsnd.egg-info/not-zip-safe
distributions_ms_dsnd.egg-info/top_level.txt