Metadata-Version: 1.0
Name: distributions-ms-dsnd
Version: 0.1
Summary: Gaussian and Binomial distributions
Home-page: UNKNOWN
Author: Mehreen Samad
Author-email: mehreen.samad@gmail.com
License: UNKNOWN
Platform: UNKNOWN
